[{"report_year":"2022","measurement_year":"2022","payer":"Commercial HMO","plan_id":"1040678","plan_name":"Univera Healthcare","region":"Western","county":"erie","member_services":"1-800-427-8490","website":{"url":"http:\/\/www.univerahealthcare.com"},"ncqa_accreditation":"Accredited","statewide_enrollment":"NA","product_availability":"YES"},{"report_year":"2022","measurement_year":"2022","payer":"Commercial HMO","plan_id":"1070680","plan_name":"Independent Health","region":"Western","county":"erie","member_services":"1-800-501-3439","website":{"url":"http:\/\/www.independenthealth.com"},"ncqa_accreditation":"Accredited","statewide_enrollment":"92582","product_availability":"YES"},{"report_year":"2022","measurement_year":"2022","payer":"Commercial HMO","plan_id":"1080383","plan_name":"MVP Health Care","region":"Western","county":"erie","member_services":"1-888-687-6277","website":{"url":"http:\/\/www.mvphealthcare.com"},"ncqa_accreditation":"Accredited","statewide_enrollment":"78643","product_availability":null},{"report_year":"2022","measurement_year":"2022","payer":"Commercial HMO","plan_id":"1140685","plan_name":"Highmark Western and Northeastern New York, Inc.","region":"Western","county":"erie","member_services":"1-866-231-0847","website":{"url":"http:\/\/www.highmark.com"},"ncqa_accreditation":"Accredited","statewide_enrollment":"324476","product_availability":"YES"},{"report_year":"2022","measurement_year":"2022","payer":"Commercial HMO","plan_id":"1390598","plan_name":"Excellus BlueCross BlueShield","region":"Western","county":"erie","member_services":"1-800-499-1275","website":{"url":"http:\/\/www.excellusbcbs.com"},"ncqa_accreditation":"Accredited","statewide_enrollment":"862694","product_availability":null},{"report_year":"2022","measurement_year":"2022","payer":"Essential Plans","plan_id":"1070680","plan_name":"Independent Health","region":"Western","county":"erie","member_services":"1-800-501-3439","website":{"url":"http:\/\/www.independenthealth.com"},"ncqa_accreditation":null,"statewide_enrollment":"6884","product_availability":"YES"},{"report_year":"2022","measurement_year":"2022","payer":"Essential Plans","plan_id":"1080383","plan_name":"MVP Health Plan","region":"Western","county":"erie","member_services":"1-888-687-6277","website":{"url":"http:\/\/www.mvphealthcare.com"},"ncqa_accreditation":null,"statewide_enrollment":"25370","product_availability":null},{"report_year":"2022","measurement_year":"2022","payer":"Essential Plans","plan_id":"1140685","plan_name":"Highmark Western and Northeastern New York, Inc.","region":"Western","county":"erie","member_services":"1-888-835-2959","website":{"url":"http:\/\/www.highmark.com"},"ncqa_accreditation":null,"statewide_enrollment":"5511","product_availability":"YES"},{"report_year":"2022","measurement_year":"2022","payer":"Essential Plans","plan_id":"1260187","plan_name":"United Healthcare","region":"Western","county":"erie","member_services":"1-888-617-8979","website":{"url":"http:\/\/www.uhc.com"},"ncqa_accreditation":null,"statewide_enrollment":"92286","product_availability":"YES"},{"report_year":"2022","measurement_year":"2022","payer":"Essential Plans","plan_id":"1390598","plan_name":"Excellus BlueCross BlueShield","region":"Western","county":"erie","member_services":"1-800-722-7884","website":{"url":"http:\/\/www.excellusbcbs.com"},"ncqa_accreditation":null,"statewide_enrollment":"51148","product_availability":null},{"report_year":"2022","measurement_year":"2022","payer":"Essential Plans","plan_id":"2060193","plan_name":"Fidelis Care","region":"Western","county":"erie","member_services":"1-888-343-3547","website":{"url":"http:\/\/www.fideliscare.org"},"ncqa_accreditation":null,"statewide_enrollment":"284673","product_availability":"YES"},{"report_year":"2022","measurement_year":"2022","payer":"Essential Plans","plan_id":"2161013","plan_name":"Molina Healthcare","region":"Western","county":"erie","member_services":"1-800-223-7242","website":{"url":"http:\/\/www.molinahealthcare.com"},"ncqa_accreditation":null,"statewide_enrollment":"53214","product_availability":"YES"},{"report_year":"2022","measurement_year":"2022","payer":"Essential Plans","plan_id":"2180196","plan_name":"Empire BlueCross BlueShield HealthPlus","region":"Western","county":"erie","member_services":"1-888-809-8009","website":{"url":"http:\/\/www.empireblue.com"},"ncqa_accreditation":null,"statewide_enrollment":"73760","product_availability":null},{"report_year":"2022","measurement_year":"2022","payer":"Medicaid Managed Care","plan_id":"1070680","plan_name":"Independent Health","region":"Western","county":"erie","member_services":"1-800-501-3439","website":{"url":"http:\/\/www.independenthealth.com"},"ncqa_accreditation":"Not Accredited","statewide_enrollment":"80062","product_availability":"C,M"},{"report_year":"2022","measurement_year":"2022","payer":"Medicaid Managed Care","plan_id":"1080383","plan_name":"MVP Health Care","region":"Western","county":"erie","member_services":"1-800-852-7826","website":{"url":"http:\/\/www.mvphealthcare.com"},"ncqa_accreditation":"Not Accredited","statewide_enrollment":"247186","product_availability":null},{"report_year":"2022","measurement_year":"2022","payer":"Medicaid Managed Care","plan_id":"1140685","plan_name":"Highmark Western and Northeastern New York, Inc.","region":"Western","county":"erie","member_services":"1-866-231-0847","website":{"url":"http:\/\/www.highmark.com"},"ncqa_accreditation":"Not Accredited","statewide_enrollment":"62093","product_availability":"C,M"},{"report_year":"2022","measurement_year":"2022","payer":"Medicaid Managed Care","plan_id":"1260187","plan_name":"UnitedHealthcare Community Plan","region":"Western","county":"erie","member_services":"1-800-493-4647","website":{"url":"http:\/\/www.uhc.com"},"ncqa_accreditation":"Accredited","statewide_enrollment":"416833","product_availability":"C,M"},{"report_year":"2022","measurement_year":"2022","payer":"Medicaid Managed Care","plan_id":"1390598","plan_name":"Excellus BlueCross BlueShield","region":"Western","county":"erie","member_services":"1-800-499-1275","website":{"url":"http:\/\/www.excellusbcbs.com"},"ncqa_accreditation":"Accredited","statewide_enrollment":"274319","product_availability":"C,M"},{"report_year":"2022","measurement_year":"2022","payer":"Medicaid Managed Care","plan_id":"2060193","plan_name":"Fidelis Care New York, Inc.","region":"Western","county":"erie","member_services":"1-888-343-3547","website":{"url":"http:\/\/www.fideliscare.org"},"ncqa_accreditation":"Accredited","statewide_enrollment":"1994789","product_availability":"C,M"}]